{
  "notebook_run_id": "r004",
  "git_sha": "ed141d7 (dirty)",
  "duration_s": 689.6,
  "duration": "11m 30s",
  "tier": "small",
  "config": {
    "tier": "small",
    "dataset": "mnist",
    "models": [
      "coba",
      "ping"
    ],
    "theta_u_grid_spikes": [
      5.0,
      2.0,
      1.0,
      0.5,
      0.2
    ],
    "theta_u_grid_hz": [
      25.0,
      10.0,
      5.0,
      2.5,
      1.0
    ],
    "max_samples": 500,
    "epochs": 10,
    "t_ms": 200.0,
    "dt": 0.1,
    "seeds_baseline": [
      42,
      43,
      44
    ],
    "seed_sweep": 42,
    "fr_strength_upper": 0.001
  },
  "results": [
    {
      "model": "coba",
      "theta_u": null,
      "theta_display": "off",
      "theta_u_hz": null,
      "seed": 42,
      "best_acc": 89.75,
      "best_epoch": 87,
      "final_acc": 89.75,
      "rate_e": 96.32703399658203
    },
    {
      "model": "coba",
      "theta_u": null,
      "theta_display": "off",
      "theta_u_hz": null,
      "seed": 43,
      "best_acc": 90.25,
      "best_epoch": 82,
      "final_acc": 89.75,
      "rate_e": 96.96722412109375
    },
    {
      "model": "coba",
      "theta_u": null,
      "theta_display": "off",
      "theta_u_hz": null,
      "seed": 44,
      "best_acc": 90.5,
      "best_epoch": 99,
      "final_acc": 90.5,
      "rate_e": 96.37586212158203
    },
    {
      "model": "coba",
      "theta_u": 5.0,
      "theta_display": "5",
      "theta_u_hz": 25.0,
      "seed": 42,
      "best_acc": 81.25,
      "best_epoch": 99,
      "final_acc": 81.0,
      "rate_e": 26.98025131225586
    },
    {
      "model": "coba",
      "theta_u": 2.0,
      "theta_display": "2",
      "theta_u_hz": 10.0,
      "seed": 42,
      "best_acc": 75.0,
      "best_epoch": 91,
      "final_acc": 73.5,
      "rate_e": 7.70399284362793
    },
    {
      "model": "coba",
      "theta_u": 1.0,
      "theta_display": "1",
      "theta_u_hz": 5.0,
      "seed": 42,
      "best_acc": 72.75,
      "best_epoch": 9,
      "final_acc": 65.0,
      "rate_e": 1.4105901718139648
    },
    {
      "model": "coba",
      "theta_u": 0.5,
      "theta_display": "0.5",
      "theta_u_hz": 2.5,
      "seed": 42,
      "best_acc": 68.0,
      "best_epoch": 9,
      "final_acc": 63.0,
      "rate_e": 0.0922309011220932
    },
    {
      "model": "coba",
      "theta_u": 0.2,
      "theta_display": "0.2",
      "theta_u_hz": 1.0,
      "seed": 42,
      "best_acc": 62.25,
      "best_epoch": 10,
      "final_acc": 54.25,
      "rate_e": 0.0
    },
    {
      "model": "ping",
      "theta_u": null,
      "theta_display": "off",
      "theta_u_hz": null,
      "seed": 42,
      "best_acc": 89.5,
      "best_epoch": 64,
      "final_acc": 88.25,
      "rate_e": 9.85243034362793
    },
    {
      "model": "ping",
      "theta_u": null,
      "theta_display": "off",
      "theta_u_hz": null,
      "seed": 43,
      "best_acc": 89.25,
      "best_epoch": 33,
      "final_acc": 87.25,
      "rate_e": 10.81814193725586
    },
    {
      "model": "ping",
      "theta_u": null,
      "theta_display": "off",
      "theta_u_hz": null,
      "seed": 44,
      "best_acc": 89.25,
      "best_epoch": 24,
      "final_acc": 88.0,
      "rate_e": 9.944661140441895
    },
    {
      "model": "ping",
      "theta_u": 5.0,
      "theta_display": "5",
      "theta_u_hz": 25.0,
      "seed": 42,
      "best_acc": 89.75,
      "best_epoch": 87,
      "final_acc": 87.5,
      "rate_e": 9.830728530883789
    },
    {
      "model": "ping",
      "theta_u": 2.0,
      "theta_display": "2",
      "theta_u_hz": 10.0,
      "seed": 42,
      "best_acc": 89.25,
      "best_epoch": 32,
      "final_acc": 87.25,
      "rate_e": 7.7962236404418945
    },
    {
      "model": "ping",
      "theta_u": 1.0,
      "theta_display": "1",
      "theta_u_hz": 5.0,
      "seed": 42,
      "best_acc": 88.0,
      "best_epoch": 87,
      "final_acc": 87.75,
      "rate_e": 4.92078971862793
    },
    {
      "model": "ping",
      "theta_u": 0.5,
      "theta_display": "0.5",
      "theta_u_hz": 2.5,
      "seed": 42,
      "best_acc": 87.75,
      "best_epoch": 22,
      "final_acc": 85.5,
      "rate_e": 3.7326388359069824
    },
    {
      "model": "ping",
      "theta_u": 0.2,
      "theta_display": "0.2",
      "theta_u_hz": 1.0,
      "seed": 42,
      "best_acc": 86.25,
      "best_epoch": 92,
      "final_acc": 84.5,
      "rate_e": 5.16493034362793
    }
  ],
  "theta_p_fgamma": [
    {
      "model": "coba",
      "theta_u": null,
      "theta_u_hz": null,
      "seed": 42,
      "acc": 86.328125,
      "e_rate": 75.22417068481445,
      "i_rate": 0.0,
      "f_gamma": null,
      "p": null
    },
    {
      "model": "coba",
      "theta_u": 5.0,
      "theta_u_hz": 25.0,
      "seed": 42,
      "acc": 82.8125,
      "e_rate": 22.951602935791016,
      "i_rate": 0.0,
      "f_gamma": null,
      "p": null
    },
    {
      "model": "coba",
      "theta_u": 2.0,
      "theta_u_hz": 10.0,
      "seed": 42,
      "acc": 72.65625,
      "e_rate": 9.025421142578125,
      "i_rate": 0.0,
      "f_gamma": null,
      "p": null
    },
    {
      "model": "coba",
      "theta_u": 1.0,
      "theta_u_hz": 5.0,
      "seed": 42,
      "acc": 68.359375,
      "e_rate": 3.9855194091796875,
      "i_rate": 0.0,
      "f_gamma": null,
      "p": null
    },
    {
      "model": "coba",
      "theta_u": 0.5,
      "theta_u_hz": 2.5,
      "seed": 42,
      "acc": 62.109375,
      "e_rate": 2.099456787109375,
      "i_rate": 0.0,
      "f_gamma": null,
      "p": null
    },
    {
      "model": "coba",
      "theta_u": 0.2,
      "theta_u_hz": 1.0,
      "seed": 42,
      "acc": 60.9375,
      "e_rate": 1.0638236999511719,
      "i_rate": 0.0,
      "f_gamma": null,
      "p": null
    },
    {
      "model": "ping",
      "theta_u": null,
      "theta_u_hz": null,
      "seed": 42,
      "acc": 85.546875,
      "e_rate": 7.652492523193359,
      "i_rate": 35.9332275390625,
      "f_gamma": 34.877461603231374,
      "p": 0.22121766393735698
    },
    {
      "model": "ping",
      "theta_u": 5.0,
      "theta_u_hz": 25.0,
      "seed": 42,
      "acc": 84.765625,
      "e_rate": 8.414115905761719,
      "i_rate": 39.302215576171875,
      "f_gamma": 36.590163619938544,
      "p": 0.22636229948748668
    },
    {
      "model": "ping",
      "theta_u": 2.0,
      "theta_u_hz": 10.0,
      "seed": 42,
      "acc": 84.375,
      "e_rate": 6.143703460693359,
      "i_rate": 29.689865112304688,
      "f_gamma": 29.55903150551883,
      "p": 0.20984419597884485
    },
    {
      "model": "ping",
      "theta_u": 1.0,
      "theta_u_hz": 5.0,
      "seed": 42,
      "acc": 87.5,
      "e_rate": 4.803733825683594,
      "i_rate": 24.910202026367188,
      "f_gamma": 25.258371285247133,
      "p": 0.18523956512237763
    },
    {
      "model": "ping",
      "theta_u": 0.5,
      "theta_u_hz": 2.5,
      "seed": 42,
      "acc": 84.765625,
      "e_rate": 3.6084365844726562,
      "i_rate": 14.024505615234375,
      "f_gamma": 16.874582964998453,
      "p": 0.2073984375
    },
    {
      "model": "ping",
      "theta_u": 0.2,
      "theta_u_hz": 1.0,
      "seed": 42,
      "acc": 83.59375,
      "e_rate": 3.5802268981933594,
      "i_rate": 10.258865356445312,
      "f_gamma": 14.725860713517122,
      "p": 0.2256207525623886
    }
  ],
  "low_w_in_sweep": [
    {
      "w_in": 0.05,
      "best_acc": 75.0,
      "best_epoch": 9,
      "final_acc": 75.0,
      "rate_e": 5.723741054534912,
      "rate_i": 0.3038194179534912
    },
    {
      "w_in": 0.1,
      "best_acc": 80.0,
      "best_epoch": 10,
      "final_acc": 80.0,
      "rate_e": 3.4342446327209473,
      "rate_i": 10.373263359069824
    },
    {
      "w_in": 0.3,
      "best_acc": 79.0,
      "best_epoch": 10,
      "final_acc": 79.0,
      "rate_e": 4.150390625,
      "rate_i": 11.11111068725586
    },
    {
      "w_in": 1.2,
      "best_acc": 82.0,
      "best_epoch": 9,
      "final_acc": 82.0,
      "rate_e": 3.0544703006744385,
      "rate_i": 16.66666603088379
    }
  ],
  "w_in_scale_sweep": [
    {
      "cell": "ping@tu0.2",
      "scale": 0.05,
      "loss": 2.3025851249694824,
      "penalty": 0.0,
      "total_loss": 2.3025851249694824,
      "acc": 9.5,
      "rate_e": 0.0,
      "rate_i": 0.0
    },
    {
      "cell": "ping@tu0.2",
      "scale": 0.1,
      "loss": 2.3025851249694824,
      "penalty": 0.0,
      "total_loss": 2.3025851249694824,
      "acc": 9.5,
      "rate_e": 0.0,
      "rate_i": 0.0
    },
    {
      "cell": "ping@tu0.2",
      "scale": 0.15,
      "loss": 2.3025851249694824,
      "penalty": 0.0,
      "total_loss": 2.3025851249694824,
      "acc": 9.5,
      "rate_e": 0.0,
      "rate_i": 0.0
    },
    {
      "cell": "ping@tu0.2",
      "scale": 0.2,
      "loss": 2.3025843620300295,
      "penalty": 0.0,
      "total_loss": 2.3025843620300295,
      "acc": 9.5,
      "rate_e": 4.8828125e-05,
      "rate_i": 0.0
    },
    {
      "cell": "ping@tu0.2",
      "scale": 0.25,
      "loss": 2.302106761932373,
      "penalty": 0.0,
      "total_loss": 2.302106761932373,
      "acc": 9.75,
      "rate_e": 0.001416015625,
      "rate_i": 0.0
    },
    {
      "cell": "ping@tu0.2",
      "scale": 0.3,
      "loss": 2.295563039779663,
      "penalty": 0.0,
      "total_loss": 2.295563039779663,
      "acc": 15.75,
      "rate_e": 0.01368408203125,
      "rate_i": 0.0
    },
    {
      "cell": "ping@tu0.2",
      "scale": 0.35,
      "loss": 2.261462163925171,
      "penalty": 0.0,
      "total_loss": 2.261462163925171,
      "acc": 27.0,
      "rate_e": 0.0656494140625,
      "rate_i": 0.0
    },
    {
      "cell": "ping@tu0.2",
      "scale": 0.4,
      "loss": 2.1748500061035156,
      "penalty": 0.0,
      "total_loss": 2.1748500061035156,
      "acc": 37.25,
      "rate_e": 0.1969482421875,
      "rate_i": 0.0
    },
    {
      "cell": "ping@tu0.2",
      "scale": 0.45,
      "loss": 2.02802414894104,
      "penalty": 0.00010997498780488968,
      "total_loss": 2.028134123928845,
      "acc": 55.5,
      "rate_e": 0.44521484375,
      "rate_i": 0.04306640625
    },
    {
      "cell": "ping@tu0.2",
      "scale": 0.5,
      "loss": 1.8238174867630006,
      "penalty": 0.0015914623737335206,
      "total_loss": 1.825408949136734,
      "acc": 64.0,
      "rate_e": 0.7920654296875,
      "rate_i": 0.2482421875
    },
    {
      "cell": "ping@tu0.2",
      "scale": 0.55,
      "loss": 1.5837198638916015,
      "penalty": 0.009057624816894531,
      "total_loss": 1.592777488708496,
      "acc": 70.75,
      "rate_e": 1.22230224609375,
      "rate_i": 0.595654296875
    },
    {
      "cell": "ping@tu0.2",
      "scale": 0.6,
      "loss": 1.3370031690597535,
      "penalty": 0.02840096664428711,
      "total_loss": 1.3654041357040405,
      "acc": 74.5,
      "rate_e": 1.683837890625,
      "rate_i": 1.24541015625
    },
    {
      "cell": "ping@tu0.2",
      "scale": 0.65,
      "loss": 1.1251952457427978,
      "penalty": 0.06310494232177735,
      "total_loss": 1.1883001880645752,
      "acc": 79.25,
      "rate_e": 2.14190673828125,
      "rate_i": 2.036669921875
    },
    {
      "cell": "ping@tu0.2",
      "scale": 0.7,
      "loss": 0.9564411449432373,
      "penalty": 0.10400648498535156,
      "total_loss": 1.0604476299285888,
      "acc": 80.0,
      "rate_e": 2.5247802734375,
      "rate_i": 3.0107421875
    },
    {
      "cell": "ping@tu0.2",
      "scale": 0.8,
      "loss": 0.732803270816803,
      "penalty": 0.18355978393554687,
      "total_loss": 0.9163630547523498,
      "acc": 81.0,
      "rate_e": 3.0755126953125,
      "rate_i": 5.525830078125
    },
    {
      "cell": "ping@tu0.2",
      "scale": 0.9,
      "loss": 0.6229733812808991,
      "penalty": 0.25278265380859377,
      "total_loss": 0.8757560350894928,
      "acc": 82.25,
      "rate_e": 3.4466796875,
      "rate_i": 7.85537109375
    },
    {
      "cell": "ping@tu0.2",
      "scale": 1.0,
      "loss": 0.5842971634864808,
      "penalty": 0.2900612487792969,
      "total_loss": 0.8743584122657777,
      "acc": 83.0,
      "rate_e": 3.6231689453125,
      "rate_i": 10.229052734375
    },
    {
      "cell": "ping@tu0.2",
      "scale": 1.15,
      "loss": 0.5488374066352845,
      "penalty": 0.328205322265625,
      "total_loss": 0.8770427289009095,
      "acc": 82.25,
      "rate_e": 3.79066162109375,
      "rate_i": 13.274169921875
    },
    {
      "cell": "ping@tu0.2",
      "scale": 1.3,
      "loss": 0.511876323223114,
      "penalty": 0.35693109130859374,
      "total_loss": 0.8688074145317077,
      "acc": 84.0,
      "rate_e": 3.910546875,
      "rate_i": 15.470849609375
    },
    {
      "cell": "ping@tu0.2",
      "scale": 1.5,
      "loss": 0.5174214994907379,
      "penalty": 0.3916158447265625,
      "total_loss": 0.9090373442173004,
      "acc": 82.5,
      "rate_e": 4.05172119140625,
      "rate_i": 18.028125
    },
    {
      "cell": "ping@tu0.2",
      "scale": 1.75,
      "loss": 0.5266706824302674,
      "penalty": 0.4537591247558594,
      "total_loss": 0.9804298071861268,
      "acc": 82.5,
      "rate_e": 4.28543701171875,
      "rate_i": 20.4888671875
    },
    {
      "cell": "ping@tu0.2",
      "scale": 2.0,
      "loss": 0.5032821750640869,
      "penalty": 0.5163637084960938,
      "total_loss": 1.0196458835601807,
      "acc": 83.5,
      "rate_e": 4.50968017578125,
      "rate_i": 22.4740234375
    },
    {
      "cell": "ping@tu0.2",
      "scale": 2.5,
      "loss": 0.5092717576026916,
      "penalty": 0.685135986328125,
      "total_loss": 1.1944077439308165,
      "acc": 83.75,
      "rate_e": 5.04888916015625,
      "rate_i": 25.786572265625
    },
    {
      "cell": "ping@tu0.2",
      "scale": 3.0,
      "loss": 0.55157066822052,
      "penalty": 0.8451368408203125,
      "total_loss": 1.3967075090408325,
      "acc": 81.25,
      "rate_e": 5.5019775390625,
      "rate_i": 28.266552734375
    },
    {
      "cell": "coba@tu0.2",
      "scale": 0.05,
      "loss": 2.3025851249694824,
      "penalty": 0.0,
      "total_loss": 2.3025851249694824,
      "acc": 9.5,
      "rate_e": 0.0,
      "rate_i": 0.0
    },
    {
      "cell": "coba@tu0.2",
      "scale": 0.1,
      "loss": 2.3025851249694824,
      "penalty": 0.0,
      "total_loss": 2.3025851249694824,
      "acc": 9.5,
      "rate_e": 0.0,
      "rate_i": 0.0
    },
    {
      "cell": "coba@tu0.2",
      "scale": 0.15,
      "loss": 2.3025851249694824,
      "penalty": 0.0,
      "total_loss": 2.3025851249694824,
      "acc": 9.5,
      "rate_e": 0.0,
      "rate_i": 0.0
    },
    {
      "cell": "coba@tu0.2",
      "scale": 0.2,
      "loss": 2.3025851249694824,
      "penalty": 0.0,
      "total_loss": 2.3025851249694824,
      "acc": 9.5,
      "rate_e": 0.0,
      "rate_i": 0.0
    },
    {
      "cell": "coba@tu0.2",
      "scale": 0.25,
      "loss": 2.3025851249694824,
      "penalty": 0.0,
      "total_loss": 2.3025851249694824,
      "acc": 9.5,
      "rate_e": 0.0,
      "rate_i": 0.0
    },
    {
      "cell": "coba@tu0.2",
      "scale": 0.3,
      "loss": 2.3025851249694824,
      "penalty": 0.0,
      "total_loss": 2.3025851249694824,
      "acc": 9.5,
      "rate_e": 0.0,
      "rate_i": 0.0
    },
    {
      "cell": "coba@tu0.2",
      "scale": 0.35,
      "loss": 2.3025851249694824,
      "penalty": 0.0,
      "total_loss": 2.3025851249694824,
      "acc": 9.5,
      "rate_e": 0.0,
      "rate_i": 0.0
    },
    {
      "cell": "coba@tu0.2",
      "scale": 0.4,
      "loss": 2.3025851249694824,
      "penalty": 0.0,
      "total_loss": 2.3025851249694824,
      "acc": 9.5,
      "rate_e": 0.0,
      "rate_i": 0.0
    },
    {
      "cell": "coba@tu0.2",
      "scale": 0.45,
      "loss": 2.302547435760498,
      "penalty": 0.0,
      "total_loss": 2.302547435760498,
      "acc": 10.25,
      "rate_e": 0.00010986328125,
      "rate_i": 0.0
    },
    {
      "cell": "coba@tu0.2",
      "scale": 0.5,
      "loss": 2.302491798400879,
      "penalty": 0.0,
      "total_loss": 2.302491798400879,
      "acc": 10.0,
      "rate_e": 0.0017333984375,
      "rate_i": 0.0
    },
    {
      "cell": "coba@tu0.2",
      "scale": 0.55,
      "loss": 2.301793308258057,
      "penalty": 0.0,
      "total_loss": 2.301793308258057,
      "acc": 12.25,
      "rate_e": 0.00897216796875,
      "rate_i": 0.0
    },
    {
      "cell": "coba@tu0.2",
      "scale": 0.6,
      "loss": 2.299919776916504,
      "penalty": 0.0,
      "total_loss": 2.299919776916504,
      "acc": 17.75,
      "rate_e": 0.02574462890625,
      "rate_i": 0.0
    },
    {
      "cell": "coba@tu0.2",
      "scale": 0.65,
      "loss": 2.297512149810791,
      "penalty": 0.0,
      "total_loss": 2.297512149810791,
      "acc": 23.5,
      "rate_e": 0.05877685546875,
      "rate_i": 0.0
    },
    {
      "cell": "coba@tu0.2",
      "scale": 0.7,
      "loss": 2.293304233551025,
      "penalty": 0.0,
      "total_loss": 2.293304233551025,
      "acc": 31.0,
      "rate_e": 0.11505126953125,
      "rate_i": 0.0
    },
    {
      "cell": "coba@tu0.2",
      "scale": 0.8,
      "loss": 2.277964220046997,
      "penalty": 0.0,
      "total_loss": 2.277964220046997,
      "acc": 41.0,
      "rate_e": 0.31883544921875,
      "rate_i": 0.0
    },
    {
      "cell": "coba@tu0.2",
      "scale": 0.9,
      "loss": 2.25718318939209,
      "penalty": 8.493749424815179e-06,
      "total_loss": 2.2571916831415146,
      "acc": 49.25,
      "rate_e": 0.6632568359375,
      "rate_i": 0.0
    },
    {
      "cell": "coba@tu0.2",
      "scale": 1.0,
      "loss": 2.2233337593078613,
      "penalty": 0.0028416309356689455,
      "total_loss": 2.2261753902435304,
      "acc": 60.5,
      "rate_e": 1.15133056640625,
      "rate_i": 0.0
    },
    {
      "cell": "coba@tu0.2",
      "scale": 1.15,
      "loss": 2.1636951065063474,
      "penalty": 0.05927701950073242,
      "total_loss": 2.22297212600708,
      "acc": 64.25,
      "rate_e": 2.130419921875,
      "rate_i": 0.0
    },
    {
      "cell": "coba@tu0.2",
      "scale": 1.3,
      "loss": 2.094003372192383,
      "penalty": 0.2512227020263672,
      "total_loss": 2.34522607421875,
      "acc": 66.75,
      "rate_e": 3.36788330078125,
      "rate_i": 0.0
    },
    {
      "cell": "coba@tu0.2",
      "scale": 1.5,
      "loss": 1.9880141401290894,
      "penalty": 0.839813720703125,
      "total_loss": 2.8278278608322145,
      "acc": 68.25,
      "rate_e": 5.3348876953125,
      "rate_i": 0.0
    },
    {
      "cell": "coba@tu0.2",
      "scale": 1.75,
      "loss": 1.8487237787246704,
      "penalty": 2.292711181640625,
      "total_loss": 4.141434960365295,
      "acc": 67.25,
      "rate_e": 8.15023193359375,
      "rate_i": 0.0
    },
    {
      "cell": "coba@tu0.2",
      "scale": 2.0,
      "loss": 1.7024526166915894,
      "penalty": 4.68288916015625,
      "total_loss": 6.38534177684784,
      "acc": 68.0,
      "rate_e": 11.2171875,
      "rate_i": 0.0
    },
    {
      "cell": "coba@tu0.2",
      "scale": 2.5,
      "loss": 1.425426721572876,
      "penalty": 12.443091796875,
      "total_loss": 13.868518518447877,
      "acc": 71.0,
      "rate_e": 17.68446044921875,
      "rate_i": 0.0
    },
    {
      "cell": "coba@tu0.2",
      "scale": 3.0,
      "loss": 1.2139923858642578,
      "penalty": 23.9353671875,
      "total_loss": 25.149359573364258,
      "acc": 71.25,
      "rate_e": 24.2063232421875,
      "rate_i": 0.0
    }
  ]
}
