{
  "notebook_run_id": "r015",
  "git_sha": "2a2af1e (dirty)",
  "mode": "baseline",
  "tier": "large",
  "duration_s": 1047.7,
  "duration": "17m 28s",
  "config": {
    "model": "cuba",
    "dataset": "shd",
    "hidden": [
      128,
      128
    ],
    "t_ms": 1000.0,
    "dt": 1.0,
    "seed": 42,
    "max_samples": 5000,
    "epochs": 40,
    "sweep_lrs": null,
    "sweep_hiddens": null,
    "sweep_isw": null
  },
  "cells": {
    "cuba_baseline": {
      "name": "cuba_baseline",
      "model": "cuba",
      "lr": 0.03,
      "isw": 1.0,
      "isb": 10.508331944775044,
      "hidden": [
        128,
        128
      ],
      "readout": "rate",
      "best_acc": 45.9,
      "final_acc": 44.4,
      "final_loss": 0.23616343460005412,
      "run_dir": "src/artifacts/notebook/nb005/cuba_baseline"
    }
  },
  "winner": {
    "name": "cuba_baseline",
    "model": "cuba",
    "lr": 0.03,
    "isw": 1.0,
    "isb": 10.508331944775044,
    "hidden": [
      128,
      128
    ],
    "readout": "rate",
    "best_acc": 45.9,
    "final_acc": 44.4,
    "final_loss": 0.23616343460005412,
    "run_dir": "src/artifacts/notebook/nb005/cuba_baseline"
  },
  "run_finished_at": "2026-04-22T18:32:15.783675Z"
}
